aduib_mcp_router/.env.example
aduib_mcp_router/.env.production
aduib_mcp_router/__init__.py
aduib_mcp_router/_main_.py
aduib_mcp_router/aduib_app.py
aduib_mcp_router/app.py
aduib_mcp_router/app_factory.py
aduib_mcp_router/fast_mcp.py
aduib_mcp_router/mcp_factory.py
aduib_mcp_router/nacos_mcp.py
aduib_mcp_router/component/__init__.py
aduib_mcp_router/component/log/__init__.py
aduib_mcp_router/component/log/app_logging.py
aduib_mcp_router/configs/__init__.py
aduib_mcp_router/configs/app_config.py
aduib_mcp_router/configs/cors/__init__.py
aduib_mcp_router/configs/deploy/__init__.py
aduib_mcp_router/configs/logging/__init__.py
aduib_mcp_router/configs/remote/__init__.py
aduib_mcp_router/configs/remote/base.py
aduib_mcp_router/configs/remote/enums.py
aduib_mcp_router/configs/remote/nacos/__init__.py
aduib_mcp_router/configs/remote/nacos/client.py
aduib_mcp_router/configs/router/__init__.py
aduib_mcp_router/constants/__init__.py
aduib_mcp_router/examples/client_persistence_examples.py
aduib_mcp_router/libs/__init__.py
aduib_mcp_router/libs/api_key_auth.py
aduib_mcp_router/libs/contextVar_wrapper.py
aduib_mcp_router/mcp_router/__init__.py
aduib_mcp_router/mcp_router/chromadb.py
aduib_mcp_router/mcp_router/install_bun.py
aduib_mcp_router/mcp_router/install_uv.py
aduib_mcp_router/mcp_router/mcp_client.py
aduib_mcp_router/mcp_router/router_manager.py
aduib_mcp_router/mcp_router/types.py
aduib_mcp_router/mcp_router/config_loader/__init__.py
aduib_mcp_router/mcp_router/config_loader/config_loader.py
aduib_mcp_router/mcp_router/config_loader/file_loader.py
aduib_mcp_router/mcp_router/config_loader/remote_config_loader.py
aduib_mcp_router/mcp_router/config_loader/url_loader.py
aduib_mcp_router/mcp_service/__init__.py
aduib_mcp_router/mcp_service/playground.py
aduib_mcp_router/mcp_service/prompt.py
aduib_mcp_router/mcp_service/tools.py
aduib_mcp_router/utils/__init__.py
aduib_mcp_router/utils/api_key.py
aduib_mcp_router/utils/async_utils.py
aduib_mcp_router/utils/encoders.py
aduib_mcp_router-1.1.14.dist-info/METADATA
aduib_mcp_router-1.1.14.dist-info/WHEEL
aduib_mcp_router-1.1.14.dist-info/entry_points.txt
aduib_mcp_router-1.1.14.dist-info/licenses/LICENSE
aduib_mcp_router-1.1.14.dist-info/RECORD
