Metadata-Version: 2.4
Name: aduib-mcp-router
Version: 1.1.14
Summary: A Router service for MCP service discovery and routing.
Author-email: chaorenex1 <24537608z@gmail.com>
License: Apache-2.0
License-File: LICENSE
Requires-Python: >=3.11
Requires-Dist: bcrypt>=4.3.0
Requires-Dist: chromadb>=1.0.5
Requires-Dist: nacos-mcp-wrapper-python
Requires-Dist: nacos-sdk-python<=2.0.9
Requires-Dist: pydantic-settings>=2.9.1
Requires-Dist: pydantic>=2.11.3
Requires-Dist: pytz
Requires-Dist: pyyaml
